md_condition/__init__.py
md_condition/extension.py
md_condition/preprocessor.py
md_condition-0.1.8.dist-info/LICENSE
md_condition-0.1.8.dist-info/METADATA
md_condition-0.1.8.dist-info/WHEEL
md_condition-0.1.8.dist-info/top_level.txt
md_condition-0.1.8.dist-info/RECORD
