Metadata-Version: 2.1
Name: md-condition
Version: 0.1.8
Summary: Python-Markdown extension to use conditional compilations
Home-page: https://github.com/cssho/md-condition
Author: Sho Sato
Author-email: rizeupbass@gmail.com
License: MIT
Platform: UNKNOWN
Classifier: License :: OSI Approved :: MIT License
Requires-Dist: Markdown
